{
  "connector.class": "io.debezium.connector.postgresql.PostgresConnector",
  "database.dbname": "cosmos",
  "database.user": "postgres",
  "slot.name": "cosmos",
  "tasks.max": "1",
  "database.history.kafka.topic": "dbhistory.employees",
  "poll.interval": "3000",
  "database.server.name": "pg-cosmos",
  "database.port": "5432",
  "plugin.name": "pgoutput",
  "topic.prefix": "cosmosdb",
  "decimal.handling.mode": "double",
  "database.hostname": "host.docker.internal",
  "database.password": "root",
  "table.include.list": "public.employees",
  "value.converter.schemas.enable": "true",
  "value.convert": "io.confluent.connect.avro.AvroConverter",
  "value.converter.schema.registry.url": "http://schema-registry:8081",
  "key.converter.schemas.enable": "true",
  "key.converter": "io.confluent.connect.avro.AvroConverter",
  "key.converter.schema.registry.url": "http://schema-registry:8081"
}